cidpaf/__init__.py
cidpaf/kube.py
cidpaf/spark.py
cidpaf-0.3.5.dist-info/licenses/LICENSE
cidpaf-0.3.5.dist-info/METADATA
cidpaf-0.3.5.dist-info/WHEEL
cidpaf-0.3.5.dist-info/top_level.txt
cidpaf-0.3.5.dist-info/RECORD
