Metadata-Version: 2.4
Name: cidpaf
Version: 0.3.5
Summary: CIDP Airflow utilities for Kubernetes and Spark integration
Home-page: https://gitlab.cidp.io/common/pypi/cidpaf
Author: CIDP Team
Author-email: CIDP Team <kijung.park@sk.com>
License: MIT
Project-URL: Homepage, https://gitlab.cidp.io/common/pypi/cidpaf
Project-URL: Bug Reports, https://gitlab.cidp.io/common/pypi/cidpaf/-/issues
Project-URL: Source Code, https://gitlab.cidp.io/common/pypi/cidpaf
Keywords: airflow,kubernetes,spark,cidp,cidpaf
Classifier: Development Status :: 3 - Alpha
Classifier: Intended Audience :: Developers
Classifier: License :: OSI Approved :: MIT License
Classifier: Operating System :: OS Independent
Classifier: Programming Language :: Python :: 3
Classifier: Programming Language :: Python :: 3.10
Classifier: Programming Language :: Python :: 3.11
Classifier: Topic :: Software Development :: Libraries :: Python Modules
Classifier: Topic :: System :: Distributed Computing
Requires-Python: >=3.10
License-File: LICENSE
Requires-Dist: kubernetes==33.1.0
Requires-Dist: pyspark==3.5.5
Dynamic: author
Dynamic: home-page
Dynamic: license-file
Dynamic: requires-python
